famiware/__init__.py
famiware/decorators/__init__.py
famiware/decorators/require_permission.py
famiware/decorators/strip_request.py
famiware/dependencies/__init__.py
famiware/dependencies/get_authorization_result.py
famiware/dependencies/get_user.py
famiware/exceptions.py
famiware/fast_api_user.py
famiware/keycloak_backend.py
famiware/middleware.py
famiware/schemas/__init__.py
famiware/schemas/authorization_methods.py
famiware/schemas/authorization_result.py
famiware/schemas/keycloak_configuration.py
famiware/schemas/match_strategy.py
famiware-0.1.1.dist-info/METADATA
famiware-0.1.1.dist-info/WHEEL
famiware-0.1.1.dist-info/RECORD
