Metadata-Version: 2.1
Name: famiware
Version: 0.1.1
Summary: 
Author: qr3n
Author-email: qtter85@gmail.com
Requires-Python: >=3.10,<4.0
Classifier: Programming Language :: Python :: 3
Classifier: Programming Language :: Python :: 3.10
Classifier: Programming Language :: Python :: 3.11
Requires-Dist: fastapi (>=0.73.0)
Requires-Dist: install (>=1.3.5,<2.0.0)
Requires-Dist: python-keycloak (>2.14.0,<4)
